aiobtdht/__init__.py
aiobtdht/dht.py
aiobtdht/schemas.py
aiobtdht/utils.py
aiobtdht/routing_table/__init__.py
aiobtdht/routing_table/bucket.py
aiobtdht/routing_table/node.py
aiobtdht/routing_table/node_stat.py
aio_btdht-0.0.9.dist-info/LICENSE
aio_btdht-0.0.9.dist-info/METADATA
aio_btdht-0.0.9.dist-info/WHEEL
aio_btdht-0.0.9.dist-info/top_level.txt
aio_btdht-0.0.9.dist-info/zip-safe
aio_btdht-0.0.9.dist-info/RECORD
