Metadata-Version: 2.1
Name: aio-btdht
Version: 0.0.9
Summary: Asyncio Bittorrent DHT
Home-page: https://github.com/bashkirtsevich-llc/aiobtdht
Author: D.Bashkirtsevich
Author-email: bashkirtsevich@gmail.com
License: GPL3 License
Keywords: Async Bittorrent-DHT DHT
Platform: UNKNOWN
Classifier: Programming Language :: Python
Requires-Python: >=3.6.*
Requires-Dist: aio-krpc-server (==0.0.7)
